skyatc/cluster/.dockerignore
skyatc/cluster/Dockerfile
skyatc/cluster/autoscaler/autoscaler.yml
skyatc/cluster/autoscaler/cluster_autoscaler.py
skyatc/cluster/cli.py
skyatc/cluster/clouds/aws/server.py
skyatc/cluster/clouds/gcp/server.py
skyatc/cluster/cluster.py
skyatc/cluster/config.py
skyatc/cluster/k3s.yaml
skyatc/cluster/kube_util.py
skyatc/cluster/kubernetes/deployment.yml
skyatc/cluster/kubernetes/nvidia-device-plugin.yml
skyatc/cluster/kubernetes/nvidia_pod.yml
skyatc/cluster/kubernetes/pod.yml
skyatc/cluster/kubernetes/service.yml
skyatc/cluster/kubernetes/test_gpu.yml
skyatc/cluster/out
skyatc/cluster/requirements.txt
skyatc/cluster/server.py
skyatc/cluster/tests/test_integration.py
skyatc-0.1.2.dist-info/METADATA
skyatc-0.1.2.dist-info/WHEEL
skyatc-0.1.2.dist-info/entry_points.txt
skyatc-0.1.2.dist-info/RECORD
